{
  "Attention:": "DAVID DRESSER",
  "Address:": "395 DYSTER POINT BLVD SUITE 415 S. SAN FRANCISCO",
  "City": "",
  "State": "",
  "Quantity": [
    "50, 759",
    "6. 382"
  ],
  "Units": [
    "CTNS",
    "CTNS"
  ],
  "Amount": "",
  "Date": "Check#",
  "ID#": "",
  "Verification": "",
  "Ref": "",
  "Vendor#": "Check Date",
  "Description": "",
  "Account#": "",
  "Department": "",
  "Product": "",
  "Date:": "",
  "Distribution:": "Fax to Field Payments at (502) 588- 7826",
  "Pay Terms": "00000",
  "Pay Method": "Check",
  "Separate Pay-": "Y",
  "Prepared By:": "",
  "Voucher Approval:": "",
  "Account Name": "",
  "Business Unit": "",
  "Account Month": "Pay Handling",
  "Requested By:": "Robert ",
  "Dist/Asgmt C.F. #": "39A00A",
  "Promo Dates": "March 15- 19, 1999",
  "Charge To Section:": "PER ATTACHED",
  "Promotion Name": [
    "GPC BUYDOWN PROGRAMS",
    "SEE ATTACHED",
    "Section 18 Narl Chain Walgreens"
  ],
  "Promotion Number": [
    "288",
    "296"
  ],
  "Promotion Code": [
    "725",
    "725"
  ],
  "AVG Rate": [
    "$2 84",
    "$2 00"
  ],
  "Please complete the following If checked \"NO\" for corporation above:": "",
  "Pay To:": "COREMARK NTERNATIONAL",
  "Is this a corporation": [
    "Yes X",
    "No"
  ],
  "Distributor No": "20182",
  "Char No": "",
  "(Records Retention:": "30 days)",
  "Mai Check To:": "",
  "Zip Code": ""
}